SJRSdetect/DetectaFormas.py
SJRSdetect/DetectaMovCamara.py
SJRSdetect/DetectaMovFotos.py
SJRSdetect/DetectaMovVideo.py
SJRSdetect/__init__.py
SJRSdetect-1.0.0.dist-info/METADATA
SJRSdetect-1.0.0.dist-info/WHEEL
SJRSdetect-1.0.0.dist-info/top_level.txt
SJRSdetect-1.0.0.dist-info/RECORD
