Metadata-Version: 2.1
Name: SJRSdetect
Version: 1.0.0
Summary: Detecta movimiento en fotos, video y camara
Home-page: https://github.com/Stevenjoelrs/SJRdetect
Author: Stevenjoelrs
Author-email: Stevenjramossalazar@gmail.com
Project-URL: Bug Tracker, https://github.com/Stevenjoelrs/SJRdetect/issues
Classifier: Programming Language :: Python :: 3
Classifier: License :: OSI Approved :: MIT License
Classifier: Operating System :: OS Independent
Requires-Python: >=3.6
